<annotation>
	<folder>test</folder>
	<filename>cycle33.jpg</filename>
	<path>D:\test\cycle33.jpg</path>
	<source>
		<database>Unknown</database>
	</source>
	<size>
		<width>1032</width>
		<height>1032</height>
		<depth>3</depth>
	</size>
	<segmented>0</segmented>
	<object>
		<name>cycle</name>
		<pose>Unspecified</pose>
		<truncated>0</truncated>
		<difficult>0</difficult>
		<bndbox>
			<xmin>57</xmin>
			<ymin>45</ymin>
			<xmax>1005</xmax>
			<ymax>998</ymax>
		</bndbox>
	</object>
</annotation>
